dbt_bouncer/__init__.py
dbt_bouncer/check_base.py
dbt_bouncer/config_file_parser.py
dbt_bouncer/config_file_validator.py
dbt_bouncer/global_context.py
dbt_bouncer/logger.py
dbt_bouncer/main.py
dbt_bouncer/runner.py
dbt_bouncer/utils.py
dbt_bouncer/version.py
dbt_bouncer/artifact_parsers/parsers_catalog.py
dbt_bouncer/artifact_parsers/parsers_common.py
dbt_bouncer/artifact_parsers/parsers_manifest.py
dbt_bouncer/artifact_parsers/parsers_run_results.py
dbt_bouncer/artifact_parsers/dbt_cloud/catalog_latest.py
dbt_bouncer/artifact_parsers/dbt_cloud/manifest_latest.py
dbt_bouncer/artifact_parsers/dbt_cloud/run_results_latest.py
dbt_bouncer/checks/common.py
dbt_bouncer/checks/catalog/check_catalog_sources.py
dbt_bouncer/checks/catalog/check_columns.py
dbt_bouncer/checks/manifest/check_exposures.py
dbt_bouncer/checks/manifest/check_lineage.py
dbt_bouncer/checks/manifest/check_macros.py
dbt_bouncer/checks/manifest/check_metadata.py
dbt_bouncer/checks/manifest/check_models.py
dbt_bouncer/checks/manifest/check_seeds.py
dbt_bouncer/checks/manifest/check_semantic_models.py
dbt_bouncer/checks/manifest/check_snapshots.py
dbt_bouncer/checks/manifest/check_sources.py
dbt_bouncer/checks/manifest/check_unit_tests.py
dbt_bouncer/checks/run_results/check_run_results.py
dbt_bouncer-2.0.0.dist-info/licenses/LICENSE
dbt_bouncer-2.0.0.dist-info/METADATA
dbt_bouncer-2.0.0.dist-info/WHEEL
dbt_bouncer-2.0.0.dist-info/entry_points.txt
dbt_bouncer-2.0.0.dist-info/top_level.txt
dbt_bouncer-2.0.0.dist-info/RECORD
