Metadata-Version: 2.4
Name: dbt-bouncer
Version: 2.0.0
Summary: Configure and enforce conventions for your dbt project.
Author-email: Padraic Slattery <pgoslatara@gmail.com>
Maintainer-email: Padraic Slattery <pgoslatara@gmail.com>
License-Expression: MIT
Project-URL: repository, https://github.com/godatadriven/dbt-bouncer
Keywords: python,cli,dbt,CI/CD
Classifier: Programming Language :: Python
Classifier: Programming Language :: Python :: 3
Classifier: Programming Language :: Python :: 3 :: Only
Classifier: Programming Language :: Python :: 3.11
Classifier: Programming Language :: Python :: 3.12
Classifier: Programming Language :: Python :: 3.13
Classifier: Programming Language :: Python :: 3.14
Requires-Python: <3.15,>=3.11
License-File: LICENSE
Requires-Dist: click!=8.3.0,!=8.3.1,<9
Requires-Dist: dbt-artifacts-parser>=0.8
Requires-Dist: h11>=0.16.0
Requires-Dist: jellyfish<2,>=1
Requires-Dist: jinja2<4,>=3
Requires-Dist: jinja2-simple-tags<1
Requires-Dist: packaging<26
Requires-Dist: progress
Requires-Dist: pydantic<3,>=2
Requires-Dist: pytest<=10
Requires-Dist: pyyaml<7
Requires-Dist: requests<3,>=2
Requires-Dist: tabulate<1
Requires-Dist: toml<1
Requires-Dist: semver<4
Provides-Extra: dev
Requires-Dist: bandit~=1.0; extra == "dev"
Requires-Dist: dbt-core<2,>=1.11.2; extra == "dev"
Requires-Dist: dbt-duckdb~=1.0; extra == "dev"
Requires-Dist: prek<1,>=0.1; extra == "dev"
Requires-Dist: pytest-cov<8,>=5; extra == "dev"
Requires-Dist: pytest-xdist~=3.0; extra == "dev"
Requires-Dist: pyupgrade~=3.0; extra == "dev"
Requires-Dist: ruff~=0.0; extra == "dev"
Requires-Dist: shandy-sqlfmt[jinjafmt]~=0.0; extra == "dev"
Requires-Dist: ty>=0.0.7; extra == "dev"
Provides-Extra: docs
Requires-Dist: mike~=2.0; extra == "docs"
Requires-Dist: mkdocs~=1.0; extra == "docs"
Requires-Dist: mkdocstrings-python<3; extra == "docs"
Requires-Dist: mkdocs-click~=0.0; extra == "docs"
Requires-Dist: mkdocs-git-revision-date-localized-plugin~=1.0; extra == "docs"
Requires-Dist: mkdocs-material~=9.0; extra == "docs"
Requires-Dist: pymdown-extensions~=10.0; extra == "docs"
Dynamic: license-file
